README.md
setup.py
protolizer/__init__.py
protolizer/exceptions.py
protolizer/fields.py
protolizer/helpers.py
protolizer/meta.py
protolizer/serializer.py
protolizer.egg-info/PKG-INFO
protolizer.egg-info/SOURCES.txt
protolizer.egg-info/dependency_links.txt
protolizer.egg-info/top_level.txt
tests/__init__.py
tests/test_custom_response.py
tests/test_fields.py
tests/test_json_to_protobuf.py
tests/test_nested_fields.py
tests/test_pre_serialize_hook.py
tests/test_protobuf_to_json.py
tests/test_validation.py