Metadata-Version: 2.1
Name: protolizer
Version: 1.0.2
Summary: A simple library to serialize and deserialize protobuf messages
Home-page: https://github.com/its0x4d/protolizer
Author: MosyDev
Author-email: mostafa.uwsgi@gmail.com
License: GPLv3
Keywords: protobuf serialization deserialization
Platform: UNKNOWN
Classifier: Programming Language :: Python :: 3
Classifier: License :: OSI Approved :: GNU General Public License v3 (GPLv3)
